{
  "name": "cruiser_30ft",
  "length_ft": 30,
  "type": "monohull",
  "category": "cruising",
  "examples": ["Sun Odyssey 32", "Bavaria 31", "Beneteau Oceanis 31"],
  "performance_class": "slow",
  "tws_kn": [6, 8, 10, 12, 14, 16, 20, 25],
  "twa_deg": [40, 50, 60, 75, 90, 110, 135, 150, 165],
  "boat_speed_kn": [
    [3.0, 3.6, 4.0, 4.4, 4.6, 4.5, 4.0, 3.4, 2.5],
    [3.7, 4.4, 4.9, 5.3, 5.5, 5.5, 5.1, 4.6, 3.6],
    [4.3, 5.0, 5.4, 5.8, 6.0, 6.0, 5.7, 5.3, 4.4],
    [4.8, 5.4, 5.8, 6.2, 6.4, 6.5, 6.3, 6.0, 5.1],
    [5.1, 5.7, 6.1, 6.5, 6.7, 6.8, 6.7, 6.4, 5.6],
    [5.3, 5.9, 6.3, 6.6, 6.8, 7.0, 6.9, 6.7, 5.9],
    [5.4, 6.0, 6.4, 6.7, 6.9, 7.1, 7.1, 6.9, 6.2],
    [5.4, 6.0, 6.4, 6.7, 6.9, 7.1, 7.2, 7.0, 6.4]
  ]
}
